{
  "info": {
    "name": "Instagram Clone API",
    "schema": "https://schema.getpostman.com/json/collection/v2.1.0/collection.json"
  },
  "item": [
    {
      "name": "Auth",
      "item": [
        {
          "name": "Register",
          "request": {
            "method": "POST",
            "url": "{{baseUrl}}/api/auth/register",
            "body": {
              "mode": "raw",
              "raw": "{\"username\":\"test\",\"email\":\"test@test.com\",\"password\":\"password123\"}",
              "options": {
                "raw": {
                  "language": "json"
                }
              }
            }
          }
        }
        // Add more endpoints...
      ]
    }
    // Add more categories...
  ]
} 